flaskfy/__init__.py
flaskfy/main.py
flaskfy-0.1.0.dist-info/METADATA
flaskfy-0.1.0.dist-info/WHEEL
flaskfy-0.1.0.dist-info/entry_points.txt
flaskfy-0.1.0.dist-info/top_level.txt
flaskfy-0.1.0.dist-info/RECORD
